paper_inbox/__init__.py
paper_inbox/cli.py
paper_inbox/main.py
paper_inbox/modules/const.py
paper_inbox/modules/cron.py
paper_inbox/modules/dependencies.py
paper_inbox/modules/email.py
paper_inbox/modules/loggers.py
paper_inbox/modules/telegram.py
paper_inbox/modules/utils.py
paper_inbox/modules/auth/gmail.py
paper_inbox/modules/config/__init__.py
paper_inbox/modules/config/file.py
paper_inbox/modules/config/getters.py
paper_inbox/modules/config/paths.py
paper_inbox/modules/config/setters.py
paper_inbox/modules/config/validators.py
paper_inbox/modules/database/formatters.py
paper_inbox/modules/database/sqlwrapper.py
paper_inbox/modules/database/utils.py
paper_inbox/modules/pdf/exceptions.py
paper_inbox/modules/pdf/utils.py
paper_inbox/modules/pdf/validators.py
paper_inbox/modules/printer/convert.py
paper_inbox/modules/printer/cups.py
paper_inbox/modules/printer/generate.py
paper_inbox/modules/printer/utils.py
paper_inbox/modules/tui/__init__.py
paper_inbox/modules/tui/info.py
paper_inbox/modules/tui/render.py
paper_inbox/modules/tui/user.py
paper_inbox/modules/tui/utils.py
paper_inbox/modules/tui/validators.py
paper_inbox-2025.12.12.dist-info/METADATA
paper_inbox-2025.12.12.dist-info/WHEEL
paper_inbox-2025.12.12.dist-info/entry_points.txt
paper_inbox-2025.12.12.dist-info/licenses/LICENSE
paper_inbox-2025.12.12.dist-info/RECORD
