Metadata-Version: 2.4
Name: paper-inbox
Version: 2025.12.12
Summary: Lift the signal from the noise      by automatically printing out email paper copies      from the senders you do care about.
Project-URL: Homepage, https://github.com/pixelprotest/paper-inbox
Project-URL: Bug Tracker, https://github.com/pixelprotest/paper-inbox/issues
Author-email: pixelprotest <hello@pixelprotest.com>
License: MIT
License-File: LICENSE
Keywords: automation,cron,email,gmail,printer
Classifier: License :: OSI Approved :: MIT License
Classifier: Operating System :: OS Independent
Classifier: Programming Language :: Python :: 3
Requires-Python: >=3.10
Requires-Dist: click>=8.3.0
Requires-Dist: dotenv>=0.9.9
Requires-Dist: google-auth-httplib2>=0.2.1
Requires-Dist: google-auth-oauthlib>=1.2.3
Requires-Dist: platformdirs>=4.5.0
Requires-Dist: questionary>=2.1.1
Requires-Dist: rich>=14.2.0
Requires-Dist: tomli-w>=1.2.0
Requires-Dist: tomli>=2.3.0
